glcoarsener/__init__.py
glcoarsener/coarsener.py
glcoarsener/clustering/__init__.py
glcoarsener/clustering/clustering.py
glcoarsener/embedding/__init__.py
glcoarsener/embedding/embedding.py
gl_coarsener-2.0.0.dist-info/LICENSE
gl_coarsener-2.0.0.dist-info/METADATA
gl_coarsener-2.0.0.dist-info/WHEEL
gl_coarsener-2.0.0.dist-info/top_level.txt
gl_coarsener-2.0.0.dist-info/RECORD
