Metadata-Version: 2.1
Name: gl-coarsener
Version: 2.0.0
Summary: GL-Coarsener, a graph learning based coarsening method
Home-page: https://github.com/rezanmz/GL-Coarsener
Author: Reza Namazi
Author-email: rezanmz@ymail.com
License: UNKNOWN
Keywords: multigrid,gl-coarsener,graph,machine learning, graph embedding,representation learning
Platform: UNKNOWN
Classifier: Programming Language :: Python :: 3
Classifier: License :: OSI Approved :: MIT License
Classifier: Operating System :: OS Independent
Classifier: Topic :: Scientific/Engineering :: Mathematics
Classifier: Topic :: Scientific/Engineering :: Artificial Intelligence
Classifier: Intended Audience :: Science/Research
Requires-Python: >=3.6
Requires-Dist: fastnode2vec
Requires-Dist: scipy
Requires-Dist: numpy
Requires-Dist: networkx
Requires-Dist: scikit-learn
